ai_ml_sdk_vgf_library-0.8.0.data/purelib/vgf_lib/__init__.py
ai_ml_sdk_vgf_library-0.8.0.data/purelib/vgf_lib/cli.py
ai_ml_sdk_vgf_library-0.8.0.data/purelib/vgf_lib/binaries/bin/vgf_dump
ai_ml_sdk_vgf_library-0.8.0.data/purelib/vgf_lib/binaries/bin/vgf_updater
ai_ml_sdk_vgf_library-0.8.0.data/purelib/vgf_lib/binaries/include/vgf/decoder.h
ai_ml_sdk_vgf_library-0.8.0.data/purelib/vgf_lib/binaries/include/vgf/decoder.hpp
ai_ml_sdk_vgf_library-0.8.0.data/purelib/vgf_lib/binaries/include/vgf/encoder.hpp
ai_ml_sdk_vgf_library-0.8.0.data/purelib/vgf_lib/binaries/include/vgf/logging.h
ai_ml_sdk_vgf_library-0.8.0.data/purelib/vgf_lib/binaries/include/vgf/logging.hpp
ai_ml_sdk_vgf_library-0.8.0.data/purelib/vgf_lib/binaries/include/vgf/types.hpp
ai_ml_sdk_vgf_library-0.8.0.data/purelib/vgf_lib/binaries/include/vgf/vulkan_helpers.generated.hpp
ai_ml_sdk_vgf_library-0.8.0.data/purelib/vgf_lib/binaries/include/vgf-utils/memory_map.hpp
ai_ml_sdk_vgf_library-0.8.0.data/purelib/vgf_lib/binaries/include/vgf-utils/numpy.hpp
ai_ml_sdk_vgf_library-0.8.0.data/purelib/vgf_lib/binaries/include/vgf-utils/temp_folder.hpp
ai_ml_sdk_vgf_library-0.8.0.data/purelib/vgf_lib/binaries/lib/ai-ml-sdk-vgf-library.spdx.json
ai_ml_sdk_vgf_library-0.8.0.data/purelib/vgf_lib/binaries/lib/libvgf.a
ai_ml_sdk_vgf_library-0.8.0.data/purelib/vgf_lib/binaries/lib/cmake/VGF/VGFConfig-debug.cmake
ai_ml_sdk_vgf_library-0.8.0.data/purelib/vgf_lib/binaries/lib/cmake/VGF/VGFConfig-release.cmake
ai_ml_sdk_vgf_library-0.8.0.data/purelib/vgf_lib/binaries/lib/cmake/VGF/VGFConfig.cmake
ai_ml_sdk_vgf_library-0.8.0.data/purelib/vgf_lib/binaries/lib/cmake/VGF/VGFConfigVersion.cmake
ai_ml_sdk_vgf_library-0.8.0.dist-info/METADATA
ai_ml_sdk_vgf_library-0.8.0.dist-info/WHEEL
ai_ml_sdk_vgf_library-0.8.0.dist-info/entry_points.txt
ai_ml_sdk_vgf_library-0.8.0.dist-info/top_level.txt
ai_ml_sdk_vgf_library-0.8.0.dist-info/RECORD
