Metadata-Version: 2.4
Name: ai_ml_sdk_vgf_library
Version: 0.8.0
Summary: ML SDK VGF Library
